qdesc/__init__.py
qdesc/update_checker.py
qdesc-1.0.9.5.dist-info/licenses/LICENCE.txt
qdesc-1.0.9.5.dist-info/METADATA
qdesc-1.0.9.5.dist-info/WHEEL
qdesc-1.0.9.5.dist-info/top_level.txt
qdesc-1.0.9.5.dist-info/RECORD
