Metadata-Version: 2.4
Name: qdesc
Version: 1.0.9.5
Summary: Quick and Easy way to do descriptive analysis.
Author: Paolo Hilado
Author-email: datasciencepgh@proton.me
License-File: LICENCE.txt
Requires-Dist: pandas
Requires-Dist: numpy
Requires-Dist: scipy
Requires-Dist: seaborn
Requires-Dist: matplotlib
Requires-Dist: statsmodels
Dynamic: author
Dynamic: author-email
Dynamic: description
Dynamic: description-content-type
Dynamic: license-file
Dynamic: requires-dist
Dynamic: summary
